README.rst
download_lt.py
setup.cfg
setup.py
setup_language_tool.py
language_tool/__init__.py
language_tool/__main__.py
language_tool/console_mode.py
language_tool/which.py
language_tool.egg-info/PKG-INFO
language_tool.egg-info/SOURCES.txt
language_tool.egg-info/dependency_links.txt
language_tool.egg-info/not-zip-safe
language_tool.egg-info/top_level.txt
language_tool/backports/__init__.py
language_tool/backports/subprocess.py