Metadata-Version: 1.1
Name: language_tool
Version: 0.3
Summary: LanguageTool through server mode
Home-page: https://bitbucket.org/spirit/language_tool
Author: spirit
Author-email: hiddenspirit@gmail.com
License: UNKNOWN
Download-URL: https://bitbucket.org/spirit/language_tool/downloads
Platform: UNKNOWN
Classifier: Development Status :: 3 - Alpha
Classifier: License :: OSI Approved :: GNU Lesser General Public License v3 or later (LGPLv3+)
Classifier: Programming Language :: Python :: 2.7
Classifier: Programming Language :: Python :: 3
Classifier: Programming Language :: Python :: 3.2
